flask_gnupg.py
Flask_GnuPG-1.0.0.dist-info/DESCRIPTION.rst
Flask_GnuPG-1.0.0.dist-info/METADATA
Flask_GnuPG-1.0.0.dist-info/RECORD
Flask_GnuPG-1.0.0.dist-info/WHEEL
Flask_GnuPG-1.0.0.dist-info/metadata.json
Flask_GnuPG-1.0.0.dist-info/top_level.txt
