Metadata-Version: 2.0
Name: Flask-GnuPG
Version: 1.0.0
Summary: Flask extension for work with GnuPG
Home-page: https://github.com/EldarAliiev/flask-gnupg
Author: Eldar Aliiev
Author-email: e.aliiev@vnmu.edu.ua
License: MIT
Download-URL: https://github.com/EldarAliiev/flask-gnupg/archive/master.zip
Keywords: Flask,GnuPG,PGP
Platform: UNKNOWN
Classifier: Development Status :: 5 - Production/Stable
Classifier: Natural Language :: English
Classifier: License :: OSI Approved :: MIT License
Classifier: Operating System :: OS Independent
Classifier: Intended Audience :: Developers
Classifier: Intended Audience :: System Administrators
Classifier: Programming Language :: Python :: 3
Classifier: Programming Language :: Python :: 3.4
Classifier: Programming Language :: Python :: 3.5
Classifier: Programming Language :: Python :: 3.6
Classifier: Topic :: Internet :: WWW/HTTP :: Dynamic Content
Classifier: Topic :: Software Development :: Libraries :: Python Modules
Requires-Python: >=3.4
Requires-Dist: Flask (>=0.12.2)
Requires-Dist: python-gnupg (>=0.4.1)
